{"py/object": "rasa.core.featurizers.tracker_featurizers.MaxHistoryTrackerFeaturizer", "state_featurizer": {"py/object": "rasa.core.featurizers.single_state_featurizer.SingleStateFeaturizer", "_default_feature_states": {"intent": {"GV": 0, "affirm": 1, "ask_budget": 2, "ask_flight": 3, "ask_join_gv": 4, "ask_requirements": 5, "back": 6, "bot_challenge": 7, "deny": 8, "faq_about_aiesec": 9, "faq_apply_volunteering": 10, "faq_how_to_apply": 11, "goodbye": 12, "greet": 13, "inform_accommodation": 14, "inform_benefits": 15, "inform_country": 16, "inform_country_and_timeline": 17, "inform_interests": 18, "inform_meal": 19, "inform_skills": 20, "inform_timeline": 21, "inquire_accommodation": 22, "inquire_aiesec_project": 23, "inquire_cop_activities": 24, "inquire_cop_contact": 25, "inquire_cop_program": 26, "inquire_countries_available": 27, "inquire_intake_process": 28, "inquire_ly_activities": 29, "inquire_ly_contact": 30, "inquire_ly_program": 31, "inquire_meal": 32, "inquire_myv": 33, "inquire_program_details": 34, "inquire_program_fee": 35, "inquire_speakup_activities": 36, "inquire_speakup_contact": 37, "inquire_speakup_program": 38, "inquire_volunteer_programs": 39, "mood_great": 40, "mood_unhappy": 41, "nlu_fallback": 42, "out_of_scope": 43, "provide_country": 44, "restart": 45, "session_start": 46}, "action_name": {"action_listen": 0, "action_restart": 1, "action_session_start": 2, "action_default_fallback": 3, "action_deactivate_loop": 4, "action_revert_fallback_events": 5, "action_default_ask_affirmation": 6, "action_default_ask_rephrase": 7, "action_two_stage_fallback": 8, "action_unlikely_intent": 9, "action_back": 10, "...": 11, "action_extract_slots": 12, "action_welcome": 13, "action_answer_question": 14, "action_faq": 15, "action_search_programs": 16, "action_ask_country": 17, "action_ask_timeline": 18, "action_ask_interests": 19, "action_ask_accommodation": 20, "action_ask_meal": 21, "action_show_program_details": 22, "action_list_countries_available": 23, "action_list_volunteer_programs": 24, "utter_aiesec_project": 25, "utter_ask_accommodation": 26, "utter_ask_benefits": 27, "utter_ask_country": 28, "utter_ask_flight": 29, "utter_ask_interests": 30, "utter_ask_skills": 31, "utter_ask_timeline": 32, "utter_budget": 33, "utter_cheer_up": 34, "utter_clean_our_plate": 35, "utter_clean_our_plate_activities": 36, "utter_clean_our_plate_contact": 37, "utter_default": 38, "utter_did_that_help": 39, "utter_faq_about_aiesec": 40, "utter_faq_documents_required": 41, "utter_faq_global_volunteer_requirements": 42, "utter_faq_how_to_apply": 43, "utter_goodbye": 44, "utter_greet": 45, "utter_gv_requirements": 46, "utter_happy": 47, "utter_iamabot": 48, "utter_intake_process": 49, "utter_join_gv": 50, "utter_love_yourself": 51, "utter_love_yourself_activities": 52, "utter_love_yourself_contact": 53, "utter_myv": 54, "utter_program_details_not_found": 55, "utter_program_fee": 56, "utter_speak_up": 57, "utter_speak_up_activities": 58, "utter_speak_up_contact": 59, "utter_suggest_programs": 60, "utter_welcome": 61, "utter_what_is_gv": 62}, "entities": {"accommodation": 0, "benefits": 1, "country": 2, "end_month": 3, "interests": 4, "meal": 5, "myv_program": 6, "program": 7, "project": 8, "skills": 9, "start_month": 10}, "slots": {"suggested_program_0": 0, "country_0": 1, "start_month_0": 2, "end_month_0": 3, "interests_0": 4, "program_0": 5, "skills_0": 6, "accommodation_0": 7, "meal_0": 8}, "active_loop": {}}, "action_texts": [], "entity_tag_specs": []}, "max_history": 5, "remove_duplicates": true}